emapsCifFile/CifFile_module.py
emapsCifFile/StarFile.py
emapsCifFile/StarScan.cp37-win_amd64.pyd
emapsCifFile/TypeContentsParser.py
emapsCifFile/YappsStarParser_1_0.py
emapsCifFile/YappsStarParser_1_1.py
emapsCifFile/YappsStarParser_2_0.py
emapsCifFile/YappsStarParser_STAR2.py
emapsCifFile/__init__.py
emapsCifFile/parsetab.py
emapsCifFile/yapps3_compiled_rt.py
emapsCifFile/drel/__init__.py
emapsCifFile/drel/drel_ast_yacc.py
emapsCifFile/drel/drel_lex.py
emapsCifFile/drel/drel_runtime.py
emapsCifFile/drel/parsetab.py
emapsCifFile/drel/py_from_ast.py
PyemapsCifReader-1.0.2.dist-info/LICENSE
PyemapsCifReader-1.0.2.dist-info/METADATA
PyemapsCifReader-1.0.2.dist-info/WHEEL
PyemapsCifReader-1.0.2.dist-info/top_level.txt
PyemapsCifReader-1.0.2.dist-info/RECORD
